cell_gater/__init__.py
cell_gater/__main__.py
cell_gater/napari.yaml
cell_gater/model/__init__.py
cell_gater/model/data_model.py
cell_gater/utils/__init__.py
cell_gater/utils/csv_df.py
cell_gater/utils/misc.py
cell_gater/widgets/__init__.py
cell_gater/widgets/sample_widget.py
cell_gater/widgets/scatter_widget.py
napari_cell_gater/__init__.py
napari_cell_gater-0.5.1.dist-info/licenses/LICENSE
napari_cell_gater-0.5.1.dist-info/METADATA
napari_cell_gater-0.5.1.dist-info/WHEEL
napari_cell_gater-0.5.1.dist-info/entry_points.txt
napari_cell_gater-0.5.1.dist-info/top_level.txt
napari_cell_gater-0.5.1.dist-info/RECORD
