Metadata-Version: 2.4
Name: napari-cell-gater
Version: 0.5.1
Author-email: Jose Nimo <nimojose@gmail.com>, Wouter-Michiel Vierdag <w-mv@hotmail.com>
Maintainer-email: Jose Nimo <nimojose@gmail.com>, Wouter-Michiel Vierdag <w-mv@hotmail.com>
Project-URL: Homepage, https://github.com/CosciaLab/napari-cell-gater
Project-URL: Source, https://github.com/CosciaLab/napari-cell-gater
Requires-Python: >=3.10
License-File: LICENSE
Requires-Dist: numpy
Requires-Dist: magicgui
Requires-Dist: qtpy
Requires-Dist: scikit-image
Requires-Dist: loguru
Requires-Dist: napari
Requires-Dist: dask-image
Requires-Dist: matplotlib
Requires-Dist: pandas
Provides-Extra: dev
Requires-Dist: pytest; extra == "dev"
Requires-Dist: pytest-cov; extra == "dev"
Requires-Dist: pytest-qt; extra == "dev"
Requires-Dist: pre-commit; extra == "dev"
Requires-Dist: ruff; extra == "dev"
Requires-Dist: tox; extra == "dev"
Requires-Dist: hatchling; extra == "dev"
Requires-Dist: PyQt5; extra == "dev"
Requires-Dist: sphinx; extra == "dev"
Requires-Dist: myst-parser; extra == "dev"
Requires-Dist: sphinx-rtd-theme; extra == "dev"
Requires-Dist: twine; extra == "dev"
Dynamic: license-file
